global oComputer, oAvatar, bDebugCollision

on mouseUp me
  [  0] pushcons 0 .............................. <"i">
  [  2] pusharglist 1 ........................... <"i">
  [  4] extcall 473 ............................. <keyPressed("i")>
  [  7] pushcons 1 .............................. <"n">
  [  9] pusharglist 1 ........................... <"n">
  [ 11] extcall 473 ............................. <keyPressed("n")>
  [ 14] and ..................................... <keyPressed("i") and keyPressed("n")>
  [ 15] pushcons 2 .............................. <"t">
  [ 17] pusharglist 1 ........................... <"t">
  [ 19] extcall 473 ............................. <keyPressed("t")>
  [ 22] and ..................................... <keyPressed("i") and keyPressed("n") and keyPressed("t")>
  [ 23] pushcons 3 .............................. <"f">
  [ 25] pusharglist 1 ........................... <"f">
  [ 27] extcall 473 ............................. <keyPressed("f")>
  [ 30] and ..................................... <keyPressed("i") and keyPressed("n") and keyPressed("t") and keyPressed("f")>
  [ 31] jmpifz [ 82] ............................ if keyPressed("i") and keyPressed("n") and keyPressed("t") and keyPressed("f") then / else
  [ 34] getglobal 58 ............................ <oComputer>
  [ 36] pusharglistnoret 1 ...................... <oComputer>
  [ 38] objcall 1 ............................... oComputer.cheatToolList()
  [ 40] getglobal 97 ............................ <oAvatar>
  [ 42] pushint8 5 .............................. <5>
  [ 44] pushint8 10 ............................. <10>
  [ 46] pusharglistnoret 3 ...................... <oAvatar, 5, 10>
  [ 48] objcall 209 ............................. oAvatar.setCurrentSquare(5, 10)
  [ 50] getglobal 58 ............................ <oComputer>
  [ 52] getglobal 58 ............................ <oComputer>
  [ 54] pusharglist 1 ........................... <oComputer>
  [ 56] objcall 31 .............................. <oComputer.getComputerTool()>
  [ 58] pusharglistnoret 2 ...................... <oComputer, oComputer.getComputerTool()>
  [ 60] objcall 36 .............................. oComputer.pickUpTool(oComputer.getComputerTool())
  [ 62] getglobal 97 ............................ <oAvatar>
  [ 64] getglobal 58 ............................ <oComputer>
  [ 66] pusharglist 1 ........................... <oComputer>
  [ 68] objcall 31 .............................. <oComputer.getComputerTool()>
  [ 70] pusharglistnoret 2 ...................... <oAvatar, oComputer.getComputerTool()>
  [ 72] objcall 36 .............................. oAvatar.pickUpTool(oComputer.getComputerTool())
  [ 74] getglobal 58 ............................ <oComputer>
  [ 76] pushzero ................................ <0>
  [ 77] setobjprop 91 ........................... oComputer.bICheated = 0
  [ 79] jmp [198]
  [ 82] pushcons 4 .............................. <"r">
  [ 84] pusharglist 1 ........................... <"r">
  [ 86] extcall 473 ............................. <keyPressed("r")>
  [ 89] pushcons 5 .............................. <"y">
  [ 91] pusharglist 1 ........................... <"y">
  [ 93] extcall 473 ............................. <keyPressed("y")>
  [ 96] and ..................................... <keyPressed("r") and keyPressed("y")>
  [ 97] pushcons 6 .............................. <"4">
  [ 99] pusharglist 1 ........................... <"4">
  [101] extcall 473 ............................. <keyPressed("4")>
  [104] and ..................................... <keyPressed("r") and keyPressed("y") and keyPressed("4")>
  [105] pushcons 1 .............................. <"n">
  [107] pusharglist 1 ........................... <"n">
  [109] extcall 473 ............................. <keyPressed("n")>
  [112] and ..................................... <keyPressed("r") and keyPressed("y") and keyPressed("4") and keyPressed("n")>
  [113] jmpifz [165] ............................ if keyPressed("r") and keyPressed("y") and keyPressed("4") and keyPressed("n") then / else
  [116] getglobal 58 ............................ <oComputer>
  [118] pusharglistnoret 1 ...................... <oComputer>
  [120] objcall 1 ............................... oComputer.cheatToolList()
  [122] getglobal 97 ............................ <oAvatar>
  [124] pushint8 5 .............................. <5>
  [126] pushint8 10 ............................. <10>
  [128] pusharglistnoret 3 ...................... <oAvatar, 5, 10>
  [130] objcall 209 ............................. oAvatar.setCurrentSquare(5, 10)
  [132] getglobal 58 ............................ <oComputer>
  [134] getglobal 58 ............................ <oComputer>
  [136] pusharglist 1 ........................... <oComputer>
  [138] objcall 31 .............................. <oComputer.getComputerTool()>
  [140] pusharglistnoret 2 ...................... <oComputer, oComputer.getComputerTool()>
  [142] objcall 36 .............................. oComputer.pickUpTool(oComputer.getComputerTool())
  [144] getglobal 97 ............................ <oAvatar>
  [146] getglobal 58 ............................ <oComputer>
  [148] pusharglist 1 ........................... <oComputer>
  [150] objcall 31 .............................. <oComputer.getComputerTool()>
  [152] pusharglistnoret 2 ...................... <oAvatar, oComputer.getComputerTool()>
  [154] objcall 36 .............................. oAvatar.pickUpTool(oComputer.getComputerTool())
  [156] getglobal 58 ............................ <oComputer>
  [158] pushint8 1 .............................. <1>
  [160] setobjprop 91 ........................... oComputer.bICheated = 1
  [162] jmp [198]
  [165] pushcons 7 .............................. <"c">
  [167] pusharglist 1 ........................... <"c">
  [169] extcall 473 ............................. <keyPressed("c")>
  [172] pushcons 8 .............................. <"o">
  [174] pusharglist 1 ........................... <"o">
  [176] extcall 473 ............................. <keyPressed("o")>
  [179] and ..................................... <keyPressed("c") and keyPressed("o")>
  [180] pushcons 9 .............................. <"l">
  [182] pusharglist 1 ........................... <"l">
  [184] extcall 473 ............................. <keyPressed("l")>
  [187] and ..................................... <keyPressed("c") and keyPressed("o") and keyPressed("l")>
  [188] jmpifz [198] ............................ if keyPressed("c") and keyPressed("o") and keyPressed("l") then
  [191] getglobal 483 ........................... <bDebugCollision>
  [194] not ..................................... <not bDebugCollision>
  [195] setglobal 483 ........................... bDebugCollision = not bDebugCollision
  [198] ret
end
