global oAvatar, oComputer, oDisplay, sInputString, sAvatarString, sScreenName, sTimeString, oIsoScene, oMap, oWhaleWashXML, oMapObject, iSledTrackValue, iBotSquareValue, oSpriteManager

on beginSprite me
  [  0] pushcons 0 .............................. <"SpriteManager">
  [  2] pusharglist 1 ........................... <"SpriteManager">
  [  4] extcall 26 .............................. <script("SpriteManager")>
  [  6] pushint16 300 ........................... <300>
  [  9] pushint16 1500 .......................... <1500>
  [ 12] pusharglist 3 ........................... <script("SpriteManager"), 300, 1500>
  [ 14] objcall 25 .............................. <script("SpriteManager").new(300, 1500)>
  [ 16] setglobal 119 ........................... oSpriteManager = script("SpriteManager").new(300, 1500)
  [ 18] pushcons 1 .............................. <"DisplayObject">
  [ 20] pusharglist 1 ........................... <"DisplayObject">
  [ 22] extcall 26 .............................. <script("DisplayObject")>
  [ 24] pusharglistnoret 1 ...................... <script("DisplayObject")>
  [ 26] objcall 25 .............................. script("DisplayObject").new()
  [ 28] pushcons 2 .............................. <"ComputerObject">
  [ 30] pusharglist 1 ........................... <"ComputerObject">
  [ 32] extcall 26 .............................. <script("ComputerObject")>
  [ 34] pusharglistnoret 1 ...................... <script("ComputerObject")>
  [ 36] objcall 25 .............................. script("ComputerObject").new()
  [ 38] getglobal 120 ........................... <oComputer>
  [ 40] pusharglistnoret 1 ...................... <oComputer>
  [ 42] objcall 121 ............................. oComputer.addToActorList()
  [ 44] pushint8 110 ............................ <110>
  [ 46] setglobal 122 ........................... iSledTrackValue = 110
  [ 48] pushint16 200 ........................... <200>
  [ 51] setglobal 123 ........................... iBotSquareValue = 200
  [ 53] pushcons 3 .............................. <"isoScene">
  [ 55] pusharglist 1 ........................... <"isoScene">
  [ 57] extcall 26 .............................. <script("isoScene")>
  [ 59] pusharglist 1 ........................... <script("isoScene")>
  [ 61] objcall 25 .............................. <script("isoScene").new()>
  [ 63] setglobal 124 ........................... oIsoScene = script("isoScene").new()
  [ 65] getglobal 124 ........................... <oIsoScene>
  [ 67] pusharglistnoret 1 ...................... <oIsoScene>
  [ 69] objcall 125 ............................. oIsoScene.init()
  [ 71] pushcons 4 .............................. <"XML">
  [ 73] pusharglist 1 ........................... <"XML">
  [ 75] extcall 127 ............................. <newObject("XML")>
  [ 77] setglobal 126 ........................... oWhaleWashXML = newObject("XML")
  [ 79] getglobal 126 ........................... <oWhaleWashXML>
  [ 81] pushint8 1 .............................. <1>
  [ 83] setobjprop 128 .......................... oWhaleWashXML.ignoreWhite = 1
  [ 85] getglobal 126 ........................... <oWhaleWashXML>
  [ 87] pushcons 5 .............................. <"hotdog">
  [ 89] pusharglist 1 ........................... <"hotdog">
  [ 91] extcall 26 .............................. <script("hotdog")>
  [ 93] pusharglist 1 ........................... <script("hotdog")>
  [ 95] objcall 687 ............................. <script("hotdog").getMap()>
  [ 98] pusharglistnoret 2 ...................... <oWhaleWashXML, script("hotdog").getMap()>
  [100] objcall 129 ............................. oWhaleWashXML.parseXML(script("hotdog").getMap())
  [102] getglobal 126 ........................... <oWhaleWashXML>
  [104] pushcons 6 .............................. <"Pathmap">
  [106] pusharglist 2 ........................... <oWhaleWashXML, "Pathmap">
  [108] extcall 130 ............................. <getNode(oWhaleWashXML, "Pathmap")>
  [110] setlocal 0 .............................. oPathMap = getNode(oWhaleWashXML, "Pathmap")
  [112] pusharglist 0 ........................... <[:]>
  [114] pushproplist ............................ <[:]>
  [115] setglobal 131 ........................... oMapObject = [:]
  [117] getglobal 131 ........................... <oMapObject>
  [119] pushsymb 132 ............................ <#rows>
  [121] getlocal 0 .............................. <oPathMap>
  [123] getchainedprop 133 ...................... <oPathMap.attributes>
  [125] getobjprop 132 .......................... <oPathMap.attributes.rows>
  [127] pusharglist 1 ........................... <oPathMap.attributes.rows>
  [129] extcall 49 .............................. <integer(oPathMap.attributes.rows)>
  [131] pusharglistnoret 3 ...................... <oMapObject, #rows, integer(oPathMap.attributes.rows)>
  [133] objcall 71 .............................. oMapObject.setaProp(#rows, integer(oPathMap.attributes.rows))
  [135] getglobal 131 ........................... <oMapObject>
  [137] pushsymb 134 ............................ <#cols>
  [139] getlocal 0 .............................. <oPathMap>
  [141] getchainedprop 133 ...................... <oPathMap.attributes>
  [143] getobjprop 134 .......................... <oPathMap.attributes.cols>
  [145] pusharglist 1 ........................... <oPathMap.attributes.cols>
  [147] extcall 49 .............................. <integer(oPathMap.attributes.cols)>
  [149] pusharglistnoret 3 ...................... <oMapObject, #cols, integer(oPathMap.attributes.cols)>
  [151] objcall 71 .............................. oMapObject.setaProp(#cols, integer(oPathMap.attributes.cols))
  [153] pusharglist 0 ........................... <[]>
  [155] pushlist ................................ <[]>
  [156] setlocal 1 .............................. templateForRows = []
  [158] pushint8 1 .............................. <1>
  [160] setlocal 2
  [162] getlocal 2
  [164] getglobal 131 ........................... <oMapObject>
  [166] getobjprop 134 .......................... <oMapObject.cols>
  [168] lteq
  [169] jmpifz [190] ............................ repeat with i = 1 to oMapObject.cols
  [172] getlocal 1 .............................. <templateForRows>
  [174] pushint8 1 .............................. <1>
  [176] inv ..................................... <-1>
  [177] pusharglistnoret 2 ...................... <templateForRows, -1>
  [179] objcall 135 ............................. templateForRows.add(-1)
  [181] pushint8 1
  [183] getlocal 2
  [185] add
  [186] setlocal 2
  [188] endrepeat [162]
  [190] getglobal 131 ........................... <oMapObject>
  [192] pushsymb 136 ............................ <#oGridVals>
  [194] pusharglist 0 ........................... <[]>
  [196] pushlist ................................ <[]>
  [197] pusharglistnoret 3 ...................... <oMapObject, #oGridVals, []>
  [199] objcall 71 .............................. oMapObject.setaProp(#oGridVals, [])
  [201] pushint8 1 .............................. <1>
  [203] setlocal 2
  [205] getlocal 2
  [207] getglobal 131 ........................... <oMapObject>
  [209] getobjprop 132 .......................... <oMapObject.rows>
  [211] lteq
  [212] jmpifz [238] ............................ repeat with i = 1 to oMapObject.rows
  [215] getglobal 131 ........................... <oMapObject>
  [217] getchainedprop 136 ...................... <oMapObject.oGridVals>
  [219] getlocal 1 .............................. <templateForRows>
  [221] pusharglist 1 ........................... <templateForRows>
  [223] objcall 137 ............................. <templateForRows.duplicate()>
  [225] pusharglistnoret 2 ...................... <oMapObject.oGridVals, templateForRows.duplicate()>
  [227] objcall 135 ............................. oMapObject.oGridVals.add(templateForRows.duplicate())
  [229] pushint8 1
  [231] getlocal 2
  [233] add
  [234] setlocal 2
  [236] endrepeat [205]
  [238] getlocal 0 .............................. <oPathMap>
  [240] pushcons 7 .............................. <"Node">
  [242] pusharglist 2 ........................... <oPathMap, "Node">
  [244] extcall 138 ............................. <getNodes(oPathMap, "Node")>
  [246] setlocal 3 .............................. oNodes = getNodes(oPathMap, "Node")
  [248] pushint8 1 .............................. <1>
  [250] setlocal 2
  [252] getlocal 2
  [254] getlocal 3 .............................. <oNodes>
  [256] getobjprop 38 ........................... <oNodes.count>
  [258] lteq
  [259] jmpifz [343] ............................ repeat with i = 1 to oNodes.count
  [262] getlocal 3 .............................. <oNodes>
  [264] getlocal 2 .............................. <i>
  [266] pusharglist 2 ........................... <oNodes, i>
  [268] objcall 39 .............................. <oNodes[i]>
  [270] getchainedprop 133 ...................... <oNodes[i].attributes>
  [272] getobjprop 139 .......................... <oNodes[i].attributes.w>
  [274] pusharglist 1 ........................... <oNodes[i].attributes.w>
  [276] extcall 49 .............................. <integer(oNodes[i].attributes.w)>
  [278] setlocal 4 .............................. w = integer(oNodes[i].attributes.w)
  [280] getlocal 3 .............................. <oNodes>
  [282] getlocal 2 .............................. <i>
  [284] pusharglist 2 ........................... <oNodes, i>
  [286] objcall 39 .............................. <oNodes[i]>
  [288] getchainedprop 133 ...................... <oNodes[i].attributes>
  [290] getobjprop 140 .......................... <oNodes[i].attributes.r>
  [292] pusharglist 1 ........................... <oNodes[i].attributes.r>
  [294] extcall 49 .............................. <integer(oNodes[i].attributes.r)>
  [296] setlocal 5 .............................. r = integer(oNodes[i].attributes.r)
  [298] getlocal 3 .............................. <oNodes>
  [300] getlocal 2 .............................. <i>
  [302] pusharglist 2 ........................... <oNodes, i>
  [304] objcall 39 .............................. <oNodes[i]>
  [306] getchainedprop 133 ...................... <oNodes[i].attributes>
  [308] getobjprop 141 .......................... <oNodes[i].attributes.c>
  [310] pusharglist 1 ........................... <oNodes[i].attributes.c>
  [312] extcall 49 .............................. <integer(oNodes[i].attributes.c)>
  [314] setlocal 6 .............................. c = integer(oNodes[i].attributes.c)
  [316] getglobal 131 ........................... <oMapObject>
  [318] pushsymb 136 ............................ <#oGridVals>
  [320] getlocal 5 .............................. <r>
  [322] pusharglist 3 ........................... <oMapObject, #oGridVals, r>
  [324] objcall 142 ............................. <oMapObject.oGridVals[r]>
  [326] getlocal 6 .............................. <c>
  [328] getlocal 4 .............................. <w>
  [330] pusharglistnoret 3 ...................... <oMapObject.oGridVals[r], c, w>
  [332] objcall 41 .............................. oMapObject.oGridVals[r][c] = w
  [334] pushint8 1
  [336] getlocal 2
  [338] add
  [339] setlocal 2
  [341] endrepeat [252]
  [343] pushint8 1 .............................. <1>
  [345] setlocal 7 .............................. iRow = 1
  [347] pushint8 1 .............................. <1>
  [349] setlocal 8 .............................. iCol = 1
  [351] pushint8 5 .............................. <5>
  [353] setlocal 9 .............................. iRows = 5
  [355] pushint8 8 .............................. <8>
  [357] setlocal 10 ............................. iCols = 8
  [359] pushint8 1 .............................. <1>
  [361] setlocal 11 ............................. iNumAvatars = 1
  [363] pushint8 6 .............................. <6>
  [365] setlocal 12 ............................. iSprite = 6
  [367] pushint8 5 .............................. <5>
  [369] setlocal 13 ............................. iShadowSprite = 5
  [371] pushint8 20 ............................. <20>
  [373] pushint16 200 ........................... <200>
  [376] pusharglist 2 ........................... <20, 200>
  [378] extcall 143 ............................. <point(20, 200)>
  [380] setlocal 14 ............................. oLoc = point(20, 200)
  [382] pushint8 50 ............................. <50>
  [384] setlocal 15 ............................. iColOff = 50
  [386] pushint8 50 ............................. <50>
  [388] setlocal 16 ............................. iRowOff = 50
  [390] pushcons 8 .............................. <"AvatarEngine">
  [392] pusharglist 1 ........................... <"AvatarEngine">
  [394] extcall 26 .............................. <script("AvatarEngine")>
  [396] getglobal 145 ........................... <sAvatarString>
  [398] pusharglist 2 ........................... <script("AvatarEngine"), sAvatarString>
  [400] objcall 25 .............................. <script("AvatarEngine").new(sAvatarString)>
  [402] setglobal 144 ........................... oAvatar = script("AvatarEngine").new(sAvatarString)
  [404] getglobal 144 ........................... <oAvatar>
  [406] getlocal 12 ............................. <iSprite>
  [408] getlocal 13 ............................. <iShadowSprite>
  [410] pusharglistnoret 3 ...................... <oAvatar, iSprite, iShadowSprite>
  [412] objcall 146 ............................. oAvatar.initSprites(iSprite, iShadowSprite)
  [414] getglobal 144 ........................... <oAvatar>
  [416] pushint8 21 ............................. <21>
  [418] pushint8 14 ............................. <14>
  [420] pusharglistnoret 3 ...................... <oAvatar, 21, 14>
  [422] objcall 147 ............................. oAvatar.setStartSquare(21, 14)
  [424] getmovieprop 23 ......................... <the actorList>
  [426] getglobal 144 ........................... <oAvatar>
  [428] pusharglistnoret 2 ...................... <the actorList, oAvatar>
  [430] objcall 135 ............................. (the actorList).add(oAvatar)
  [432] pushsymb 149 ............................ <#initMachine>
  [434] pusharglistnoret 1 ...................... <#initMachine>
  [436] extcall 148 ............................. sendAllSprites(#initMachine)
  [438] getglobal 120 ........................... <oComputer>
  [440] pusharglistnoret 1 ...................... <oComputer>
  [442] objcall 150 ............................. oComputer.gameBegin()
  [444] pusharglistnoret 0 ...................... <>
  [446] extcall 151 ............................. updateStage()
  [448] ret
end
