global sInputString, sAvatarString, sScreenName, sTimeString, sHiScoreURL, oServerHelper

on exitFrame me
  [  0] pushcons 0 .............................. <"sw1">
  [  2] pusharglist 1 ........................... <"sw1">
  [  4] extcall 799 ............................. <externalParamName("sw1")>
  [  7] pushcons 0 .............................. <"sw1">
  [  9] eq ...................................... <externalParamName("sw1") = "sw1">
  [ 10] jmpifz [ 25] ............................ if externalParamName("sw1") = "sw1" then / else
  [ 13] pushcons 0 .............................. <"sw1">
  [ 15] pusharglist 1 ........................... <"sw1">
  [ 17] extcall 800 ............................. <externalParamValue("sw1")>
  [ 20] setlocal 0 .............................. sInputData = externalParamValue("sw1")
  [ 22] jmp [ 29]
  [ 25] pushcons 1 .............................. <"c249d2hvcmZpbnxocj0wMDgvMTE1LDYxLDE3JmhkPTAwMS8xNTMsMTI2LDk5JmV5PTAwNi8yMzgsMjM4LDIzOCZmYz0wMDIvMTUzLDEyNiw5OSZiZD0wMDEvMTUzLDEyNiw5OSZsaD0wMDEvMTUzLDEyNiw5OSZyaD0wMDEvMTUzLDEyNiw5OSZjaD0wMDQvMjM4LDIzOCwyMzgmbHM9MDAxLzIzOCw2MCw0NyZycz0wMDEvMjM4LDYwLDQ3JmxnPTAwMS85NywxMjAsODUmc2g9MDAxLzUxLDUxLDUxfHN0PTIwMDQ6MDk6MDE6MTY6MDM==">
  [ 27] setlocal 0 .............................. sInputData = "c249d2hvcmZpbnxocj0wMDgvMTE1LDYxLDE3JmhkPTAwMS8xNTMsMTI2LDk5JmV5PTAwNi8yMzgsMjM4LDIzOCZmYz0wMDIvMTUzLDEyNiw5OSZiZD0wMDEvMTUzLDEyNiw5OSZsaD0wMDEvMTUzLDEyNiw5OSZyaD0wMDEvMTUzLDEyNiw5OSZjaD0wMDQvMjM4LDIzOCwyMzgmbHM9MDAxLzIzOCw2MCw0NyZycz0wMDEvMjM4LDYwLDQ3JmxnPTAwMS85NywxMjAsODUmc2g9MDAxLzUxLDUxLDUxfHN0PTIwMDQ6MDk6MDE6MTY6MDM=="
  [ 29] getlocal 0 .............................. <sInputData>
  [ 31] pusharglist 1 ........................... <sInputData>
  [ 33] extcall 801 ............................. <base64Decode(sInputData)>
  [ 36] setglobal 164 ........................... sInputString = base64Decode(sInputData)
  [ 38] getmovieprop 742 ........................ <the runMode>
  [ 41] pushcons 2 .............................. <"Author">
  [ 43] containsstr ............................. <the runMode contains "Author">
  [ 44] jmpifz [ 55] ............................ if the runMode contains "Author" then / else
  [ 47] pushcons 3 .............................. <"http://mycoke.studiocom.com/recycler.do">
  [ 49] setglobal 788 ........................... sHiScoreURL = "http://mycoke.studiocom.com/recycler.do"
  [ 52] jmp [ 95]
  [ 55] pushcons 4 .............................. <"sw2">
  [ 57] pusharglist 1 ........................... <"sw2">
  [ 59] extcall 799 ............................. <externalParamName("sw2")>
  [ 62] pushcons 4 .............................. <"sw2">
  [ 64] eq ...................................... <externalParamName("sw2") = "sw2">
  [ 65] jmpifz [ 90] ............................ if externalParamName("sw2") = "sw2" then / else
  [ 68] pushcons 4 .............................. <"sw2">
  [ 70] pusharglist 1 ........................... <"sw2">
  [ 72] extcall 800 ............................. <externalParamValue("sw2")>
  [ 75] setglobal 788 ........................... sHiScoreURL = externalParamValue("sw2")
  [ 78] getglobal 788 ........................... <sHiScoreURL>
  [ 81] pushcons 5 .............................. <"/recycler.do">
  [ 83] joinstr ................................. <sHiScoreURL & "/recycler.do">
  [ 84] setglobal 788 ........................... sHiScoreURL = sHiScoreURL & "/recycler.do"
  [ 87] jmp [ 95]
  [ 90] pushcons 6 .............................. <EMPTY>
  [ 92] setglobal 788 ........................... sHiScoreURL = EMPTY
  [ 95] pushcons 7 .............................. <"|">
  [ 97] setmovieprop 404 ........................ the itemDelimiter = "|"
  [100] getglobal 164 ........................... <sInputString>
  [102] pushsymb 406 ............................ <#item>
  [105] pushint8 1 .............................. <1>
  [107] pusharglist 3 ........................... <sInputString, #item, 1>
  [109] objcall 54 .............................. <sInputString.item[1]>
  [111] setglobal 162 ........................... sScreenName = sInputString.item[1]
  [113] getglobal 164 ........................... <sInputString>
  [115] pushsymb 406 ............................ <#item>
  [118] pushint8 2 .............................. <2>
  [120] pusharglist 3 ........................... <sInputString, #item, 2>
  [122] objcall 54 .............................. <sInputString.item[2]>
  [124] setglobal 163 ........................... sAvatarString = sInputString.item[2]
  [126] getglobal 164 ........................... <sInputString>
  [128] pushsymb 406 ............................ <#item>
  [131] pushint8 3 .............................. <3>
  [133] pusharglist 3 ........................... <sInputString, #item, 3>
  [135] objcall 54 .............................. <sInputString.item[3]>
  [137] setglobal 165 ........................... sTimeString = sInputString.item[3]
  [139] pushcons 8 .............................. <",">
  [141] setmovieprop 404 ........................ the itemDelimiter = ","
  [144] pushcons 9 .............................. <"ServerHelper">
  [146] pusharglist 1 ........................... <"ServerHelper">
  [148] extcall 64 .............................. <script("ServerHelper")>
  [150] getglobal 165 ........................... <sTimeString>
  [152] pusharglist 2 ........................... <script("ServerHelper"), sTimeString>
  [154] objcall 2 ............................... <script("ServerHelper").new(sTimeString)>
  [156] setglobal 784 ........................... oServerHelper = script("ServerHelper").new(sTimeString)
  [159] ret
end
